setup.py
deployer/__init__.py
deployer/compat.py
deployer/deploy.py
deployer/cli/__init__.py
lambda_deployer.egg-info/PKG-INFO
lambda_deployer.egg-info/SOURCES.txt
lambda_deployer.egg-info/dependency_links.txt
lambda_deployer.egg-info/entry_points.txt
lambda_deployer.egg-info/not-zip-safe
lambda_deployer.egg-info/requires.txt
lambda_deployer.egg-info/top_level.txt