Metadata-Version: 1.1
Name: lambda-deployer
Version: 0.1.0
Summary: Deployer for lambda services
Home-page: https://github.com/wscoble/lambda-deploy
Author: Scott Scoble
Author-email: scott@scoble.tech
License: Apache License 2.0
Keywords: chefit
Platform: UNKNOWN
Classifier: Development Status :: 2 - Pre-Alpha
Classifier: Intended Audience :: Developers
Classifier: License :: OSI Approved :: Apache Software License
Classifier: Natural Language :: English
Classifier: Programming Language :: Python :: 2
Classifier: Programming Language :: Python :: 2.7
